dspy_profiles/__init__.py
dspy_profiles/api.py
dspy_profiles/cli.py
dspy_profiles/commands/__init__.py
dspy_profiles/commands/delete.py
dspy_profiles/commands/diff.py
dspy_profiles/commands/import_profile.py
dspy_profiles/commands/init.py
dspy_profiles/commands/list.py
dspy_profiles/commands/run.py
dspy_profiles/commands/set.py
dspy_profiles/commands/show.py
dspy_profiles/commands/test.py
dspy_profiles/commands/validate.py
dspy_profiles/config.py
dspy_profiles/core.py
dspy_profiles/loader.py
dspy_profiles/logging_utils.py
dspy_profiles/utils.py
dspy_profiles/validation.py
dspy_profiles-0.4.0.dist-info/WHEEL
dspy_profiles-0.4.0.dist-info/entry_points.txt
dspy_profiles-0.4.0.dist-info/METADATA
dspy_profiles-0.4.0.dist-info/RECORD
