Metadata-Version: 2.3
Name: dspy-profiles
Version: 0.4.0
Summary: Awesome profiles support for D
Keywords: dspy,llm,configuration,profiles,ai
Author: Niels van Galen Last
Author-email: Niels van Galen Last <nvangalenlast@gmail.com>
License: MIT
Classifier: Development Status :: 3 - Alpha
Classifier: Intended Audience :: Developers
Classifier: License :: OSI Approved :: MIT License
Classifier: Programming Language :: Python :: 3
Classifier: Programming Language :: Python :: 3.12
Classifier: Topic :: Software Development :: Libraries :: Python Modules
Classifier: Topic :: Utilities
Requires-Dist: dspy>=3.0.2
Requires-Dist: pydantic>=2.11.7
Requires-Dist: python-dotenv>=1.1.1
Requires-Dist: rich>=14.1.0
Requires-Dist: toml>=0.10.2
Requires-Dist: typer>=0.16.1
Requires-Dist: keyring ; extra == 'keyring'
Requires-Python: >=3.12
Project-URL: Homepage, https://github.com/nielsgl/dspy-profiles
Project-URL: Repository, https://github.com/nielsgl/dspy-profiles
Provides-Extra: keyring
